virtualmouse.py
virtualmouse-0.0.2.dist-info/METADATA
virtualmouse-0.0.2.dist-info/WHEEL
virtualmouse-0.0.2.dist-info/entry_points.txt
virtualmouse-0.0.2.dist-info/top_level.txt
virtualmouse-0.0.2.dist-info/RECORD
