Metadata-Version: 2.1
Name: virtualmouse
Version: 0.0.2
Summary: virtualmouse is a virtual mouse using a finger with a camera. (This is a re-released version of virtumouse)
Home-page: https://github.com/kumanekosub/virtualmouse
Author: KO KUMADA
Author-email: s2122023@stu.musashino-u.ac.jp
License: UNKNOWN
Project-URL: Bug Tracker, https://github.com/kumanekosub/virtualmouse
Platform: UNKNOWN
Classifier: Programming Language :: Python :: 3
Classifier: License :: OSI Approved :: MIT License
Classifier: Operating System :: OS Independent
Requires-Python: >=3.8
